Metadata-Version: 2.1
Name: lqa
Version: 0.0.4
Summary: A package for automatically adjusting learning rate in the training of deep learning.
Home-page: UNKNOWN
Author: rockfc
Author-email: rozen0maiden@126.com
License: UNKNOWN
Platform: UNKNOWN
Classifier: Programming Language :: Python :: 3
Classifier: License :: OSI Approved :: MIT License
Classifier: Operating System :: OS Independent
Requires-Python: >=3.6
